terrainbento/__init__.py
terrainbento/_version.py
terrainbento/base_class/__init__.py
terrainbento/base_class/erosion_model.py
terrainbento/base_class/stochastic_erosion_model.py
terrainbento/base_class/two_lithology_erosion_model.py
terrainbento/boundary_handlers/__init__.py
terrainbento/boundary_handlers/capture_node_baselevel_handler.py
terrainbento/boundary_handlers/generic_function_baselevel_handler.py
terrainbento/boundary_handlers/not_core_node_baselevel_handler.py
terrainbento/boundary_handlers/precip_changer.py
terrainbento/boundary_handlers/single_node_baselevel_handler.py
terrainbento/clock/__init__.py
terrainbento/clock/clock.py
terrainbento/derived_models/__init__.py
terrainbento/derived_models/model_basic.py
terrainbento/derived_models/model_basicCh.py
terrainbento/derived_models/model_basicChRt.py
terrainbento/derived_models/model_basicChRtTh.py
terrainbento/derived_models/model_basicChSa.py
terrainbento/derived_models/model_basicCv.py
terrainbento/derived_models/model_basicDd.py
terrainbento/derived_models/model_basicDdHy.py
terrainbento/derived_models/model_basicDdRt.py
terrainbento/derived_models/model_basicDdSt.py
terrainbento/derived_models/model_basicDdVs.py
terrainbento/derived_models/model_basicHy.py
terrainbento/derived_models/model_basicHyRt.py
terrainbento/derived_models/model_basicHySa.py
terrainbento/derived_models/model_basicHySt.py
terrainbento/derived_models/model_basicHyVs.py
terrainbento/derived_models/model_basicRt.py
terrainbento/derived_models/model_basicRtSa.py
terrainbento/derived_models/model_basicRtTh.py
terrainbento/derived_models/model_basicRtVs.py
terrainbento/derived_models/model_basicSa.py
terrainbento/derived_models/model_basicSaVs.py
terrainbento/derived_models/model_basicSt.py
terrainbento/derived_models/model_basicStTh.py
terrainbento/derived_models/model_basicStVs.py
terrainbento/derived_models/model_basicTh.py
terrainbento/derived_models/model_basicThVs.py
terrainbento/derived_models/model_basicVs.py
terrainbento-2.0.1.dist-info/LICENSE
terrainbento-2.0.1.dist-info/METADATA
terrainbento-2.0.1.dist-info/WHEEL
terrainbento-2.0.1.dist-info/top_level.txt
terrainbento-2.0.1.dist-info/RECORD
