Metadata-Version: 2.1
Name: terrainbento
Version: 2.0.1
Summary: TerrainBento suite of landscape evolution models
Author: Katy Barnhart
Author-email: barnhark@colorado.edu
License: MIT License
Project-URL: documentation, https://terrainbento.readthedocs.io
Project-URL: repository, https://github.com/TerrainBento/terrainbento
Keywords: earth science,landlab,landscape evolution modeling,numerical modeling
Classifier: Development Status :: 4 - Beta
Classifier: Intended Audience :: Science/Research
Classifier: License :: OSI Approved :: MIT License
Classifier: Operating System :: OS Independent
Classifier: Programming Language :: Python :: 3
Classifier: Programming Language :: Python :: 3.10
Classifier: Programming Language :: Python :: 3.11
Classifier: Programming Language :: Python :: 3.12
Classifier: Programming Language :: Python :: Implementation :: CPython
Classifier: Topic :: Scientific/Engineering :: Physics
Requires-Python: >=3.10
License-File: LICENSE
Requires-Dist: dask
Requires-Dist: landlab >=2.6
Requires-Dist: numpy <2,>=1.20
Requires-Dist: pyyaml
Requires-Dist: scipy
Requires-Dist: xarray >=0.16
Provides-Extra: build
Requires-Dist: build ; extra == 'build'
Requires-Dist: twine ; extra == 'build'
Requires-Dist: zest.releaser ; extra == 'build'
Provides-Extra: dev
Requires-Dist: nox ; extra == 'dev'
Provides-Extra: docs
Requires-Dist: sphinx ; extra == 'docs'
Requires-Dist: sphinx-rtd-theme ; extra == 'docs'
Provides-Extra: notebooks
Requires-Dist: holoviews ; extra == 'notebooks'
Requires-Dist: jupyter ; extra == 'notebooks'
Requires-Dist: matplotlib ; extra == 'notebooks'
Requires-Dist: pandas ; extra == 'notebooks'
Provides-Extra: testing
Requires-Dist: coveralls ; extra == 'testing'
Requires-Dist: pytest ; extra == 'testing'
Requires-Dist: pytest-cov ; extra == 'testing'
Requires-Dist: pytest-datadir ; extra == 'testing'
